{
    "description":"",
    "params":{
        "modality":"EEG",
        "name":"HeadModel_CHBM_Multilayer",
        "description":"",
        "colormap":"tools/mycolormap.mat",        
        "bst_config":{
            "description":"",
            "protocol_name":"HeadModel_CHBM_Multilayer",
            "protocol_reset":false,          
            "bst_path":"/mnt/Develop/Tools/brainstorm3",
            "db_path":"local",
            "after_MaQC":{
                "run":false
            }
        },        
        "spm_config":{
            "description":"",
            "spm_path":"/mnt/Develop/Tools/spm12"
        },
        "bcv_config":{
            "export":true,
            "export_path":"/mnt/Store/Data/CHBM/Multilayer/BC-V_Structure"
        },
        "bst_export":{
            "description":"Folder to export the Brainstorm outputs",
            "output_path":"/mnt/Store/Data/CHBM/Multilayer/BST_Output"
        },
        "tmp_path":{
            "description":"",
            "value":"local"
        }                
    }
}